{
  "critical_config": {
    "accident_prob": 0.0,
    "auto_calibrate_thresholds": true,
    "batch_size": 64,
    "calibration_max_pairs": 20000,
    "calibration_state_count": 3000,
    "candidate_batch_evict_count": 25,
    "candidate_centroid_shift_threshold": 0.01,
    "candidate_distance_threshold": 0.25,
    "candidate_hard_limit": 150,
    "candidate_promotion_visits": 4,
    "candidate_recent_protection_episodes": 3,
    "candidate_safety_distance_threshold": 0.25,
    "candidate_similarity_threshold": 0.9,
    "candidate_stable_updates": 2,
    "capacity_fallback_general_variation": 0.1,
    "capacity_fallback_safety_improvement": 0.1,
    "capacity_review_interval": 25,
    "centroid_shift_threshold": 0.01,
    "centroid_stability_distance_threshold": 0.1,
    "centroid_stable_updates": 3,
    "close_enough_fallback": true,
    "collision_penalty": 50.0,
    "deterministic": true,
    "discrete_steering_dim": 3,
    "discrete_throttle_dim": 3,
    "gamma": 0.99,
    "hazard_memory_capacity": 125,
    "hazard_memory_fraction": 0.25,
    "hidden_size": 128,
    "hybrid_design_version": "karthikeya27adv_directional_safety_fallback_v5",
    "learning_rate": 5e-05,
    "map_blocks": 3,
    "max_candidate_centroid_updates": 4,
    "max_centroid_updates": 10,
    "max_episode_steps": 500,
    "max_state_candidates": 125,
    "max_state_pools": 500,
    "maximum_pool_capacity": 500,
    "minimum_progress_reward": 0.01,
    "out_of_road_penalty": 50.0,
    "pool_storage_dtype": "float32",
    "pool_training_fraction": 0.8,
    "progress_every": 25,
    "replay_capacity": 50000,
    "rmst_event": "collision",
    "rmst_tau": 500,
    "safe_confirmation_visits": 2,
    "safety_distance_threshold": 0.2,
    "safety_horizon_steps": 5,
    "safety_lane_boundary_cap": 10.0,
    "safety_nearest_object_cap": 100.0,
    "safety_similarity_threshold": 0.9,
    "safety_speed_cap": 200.0,
    "safety_speed_fallback_unit": "mps",
    "seed": 31,
    "state_distance_threshold": 0.2,
    "state_similarity_threshold": 0.9,
    "success_reward": 10.0,
    "target_update_steps": 1000,
    "test_episodes": 300,
    "test_seed": 100000,
    "traffic_density": 0.2,
    "train_episodes": 500,
    "warning_block_threshold": 2
  },
  "critical_config_sha256": "4eea48b2367c347bd98ef485665127bcba6529231bb587f7a051795510974d0d",
  "environment": "MetaDrive",
  "method_baseline_shared_config_sha256": {
    "Karthikeya27adv": null,
    "Karthikeya27adv20": "140b2cdc37a0cb5d8f02656b2bd4b3df5cc9f82da6f2e4f57d1c4dad384cb900",
    "Karthikeya27adv23": "140b2cdc37a0cb5d8f02656b2bd4b3df5cc9f82da6f2e4f57d1c4dad384cb900",
    "Karthikeya27adv8": "140b2cdc37a0cb5d8f02656b2bd4b3df5cc9f82da6f2e4f57d1c4dad384cb900"
  },
  "method_critical_config_sha256": {
    "Karthikeya27adv": "4eea48b2367c347bd98ef485665127bcba6529231bb587f7a051795510974d0d",
    "Karthikeya27adv20": "d32e55a73b0caa8f0a702bad26e95e2654303ef3c796735a0eb08a155aff6531",
    "Karthikeya27adv23": "3fb5282297f41d400ae6a12383c8a695a97119c977b3268cdab6789000640316",
    "Karthikeya27adv8": "b0f29725efef9644ba365a7ed4db4efeab07c9a8c94264f5f028fa5068065fca"
  },
  "method_engine_object_safety_scan": {
    "Karthikeya27adv": true,
    "Karthikeya27adv20": true,
    "Karthikeya27adv23": true,
    "Karthikeya27adv8": true
  },
  "method_observation_sources": {
    "Karthikeya27adv": "flattened_metadrive_observation_plus_engine_safety_features",
    "Karthikeya27adv20": "flattened_metadrive_observation_for_dqn_plus_engine_safety_features_during_first_pool_training_phase_only",
    "Karthikeya27adv23": "flattened_metadrive_observation_for_dqn_plus_engine_safety_features_during_first_pool_training_phase_only",
    "Karthikeya27adv8": "flattened_metadrive_observation_for_dqn_plus_engine_safety_features_during_first_pool_training_phase_only"
  },
  "methods": [
    {
      "completed": true,
      "config_sha256": "ea93a69a94e9d2a3edb75f4f6f06d139da653404f7dfe1c6c67cd5eacc2a2c20",
      "created_at_unix": 1784508050.8749444,
      "critical_config": {
        "accident_prob": 0.0,
        "auto_calibrate_thresholds": true,
        "batch_size": 64,
        "calibration_max_pairs": 20000,
        "calibration_state_count": 3000,
        "candidate_batch_evict_count": 25,
        "candidate_centroid_shift_threshold": 0.01,
        "candidate_distance_threshold": 0.25,
        "candidate_hard_limit": 150,
        "candidate_promotion_visits": 4,
        "candidate_recent_protection_episodes": 3,
        "candidate_safety_distance_threshold": 0.25,
        "candidate_similarity_threshold": 0.9,
        "candidate_stable_updates": 2,
        "capacity_fallback_general_variation": 0.1,
        "capacity_fallback_safety_improvement": 0.1,
        "capacity_review_interval": 25,
        "centroid_shift_threshold": 0.01,
        "centroid_stability_distance_threshold": 0.1,
        "centroid_stable_updates": 3,
        "close_enough_fallback": true,
        "collision_penalty": 50.0,
        "deterministic": true,
        "discrete_steering_dim": 3,
        "discrete_throttle_dim": 3,
        "gamma": 0.99,
        "hazard_memory_capacity": 125,
        "hazard_memory_fraction": 0.25,
        "hidden_size": 128,
        "hybrid_design_version": "karthikeya27adv_directional_safety_fallback_v5",
        "learning_rate": 5e-05,
        "map_blocks": 3,
        "max_candidate_centroid_updates": 4,
        "max_centroid_updates": 10,
        "max_episode_steps": 500,
        "max_state_candidates": 125,
        "max_state_pools": 500,
        "maximum_pool_capacity": 500,
        "minimum_progress_reward": 0.01,
        "out_of_road_penalty": 50.0,
        "pool_storage_dtype": "float32",
        "pool_training_fraction": 0.8,
        "progress_every": 25,
        "replay_capacity": 50000,
        "rmst_event": "collision",
        "rmst_tau": 500,
        "safe_confirmation_visits": 2,
        "safety_distance_threshold": 0.2,
        "safety_horizon_steps": 5,
        "safety_lane_boundary_cap": 10.0,
        "safety_nearest_object_cap": 100.0,
        "safety_similarity_threshold": 0.9,
        "safety_speed_cap": 200.0,
        "safety_speed_fallback_unit": "mps",
        "seed": 31,
        "state_distance_threshold": 0.2,
        "state_similarity_threshold": 0.9,
        "success_reward": 10.0,
        "target_update_steps": 1000,
        "test_episodes": 300,
        "test_seed": 100000,
        "traffic_density": 0.2,
        "train_episodes": 500,
        "warning_block_threshold": 2
      },
      "critical_config_sha256": "4eea48b2367c347bd98ef485665127bcba6529231bb587f7a051795510974d0d",
      "cuda_version": "12.8",
      "detailed_results_sha256": "08a4141c7540ce567635cd132a9d3a850a63fdb21555fb635afd608aa9f66b20",
      "device": "cuda",
      "environment": "MetaDrive",
      "metadrive_version": "unknown",
      "method": "Karthikeya27adv",
      "method_label": "Karthikeya27adv",
      "metrics_sha256": "dbf844061301522aebe42cc2dee32258bf263167beec7a5f12469b5aa3723ffe",
      "model_selection": "final_training_episode",
      "model_sha256": "09a1123471815c35352ab34d6443c3ba8df4e7f6b535f4fb222a8209b698555d",
      "observation_source": "flattened_metadrive_observation_plus_engine_safety_features",
      "phase_runtime": [
        {
          "average_cpu_time_seconds_per_episode": 28.602367827744015,
          "average_wall_time_seconds_per_episode": 2.8518591447736834,
          "episodes": 500,
          "method": "Karthikeya27adv",
          "method_label": "Karthikeya27adv",
          "phase": "train",
          "phase_cpu_time_seconds": 14816.587687060999,
          "phase_wall_time_seconds": 1524.6063887380005,
          "summed_episode_cpu_time_seconds": 14301.183913872008,
          "summed_episode_wall_time_seconds": 1425.9295723868418
        },
        {
          "average_cpu_time_seconds_per_episode": 0.9399131177966047,
          "average_wall_time_seconds_per_episode": 0.9391837315999632,
          "episodes": 300,
          "method": "Karthikeya27adv",
          "method_label": "Karthikeya27adv",
          "phase": "test",
          "phase_cpu_time_seconds": 331.8059468329993,
          "phase_wall_time_seconds": 331.54424329000176,
          "summed_episode_cpu_time_seconds": 281.9739353389814,
          "summed_episode_wall_time_seconds": 281.75511947998893
        }
      ],
      "python_version": "3.11.15",
      "results_sha256": "e3f3930afe738b0a5db88c14cff769622e05e43796876d65d51ad6e899cb7666",
      "runtime_statistics_sha256": "0e9cd64175ff132d117417fbc9c4e6445639941336100ab73cc6635d096d6124",
      "safety_memory_sha256": "83685b16b532f6abeb9b21675888ecf70f5b66e82ee1c9424b44ef40af0b54df",
      "seed": 31,
      "state_candidate_statistics_sha256": "3da5c73cd06875c56ddfe613c43576f9671d7dc96eaa08f8b2a52c6d2aee07b0",
      "state_hazard_memory_statistics_sha256": "3844bdd6080a4e25a3611a6330959fa14b64a2630051b4b85c56dc5acf6787bf",
      "state_matching_calibration_sha256": "e9df1c9a73ad23f6ed9f635c0900bf11c845c10e85926d19299e8e17720a7ef7",
      "state_matching_rejection_statistics_sha256": "b0e75414e3cd28fbd72704de85c078f1e117de481a25bc8ebaaf35f63484dd1d",
      "state_pool_capacity_growth_sha256": "6043096bb6a6d44144a637aff27040f0a7599b0067823748a8a096efe355afd1",
      "state_pool_statistics_sha256": "6476bab45f4b282250ca723526b7bf86fddb290915ea42f945b783cca7603c03",
      "state_retired_pool_statistics_sha256": "3d2f67cf3b1cfb821132b863ca06a21631fb34ff0c692167ac8844e513aff79e",
      "test_policy": "final_trained_frozen_dqn_argmax",
      "test_uses_engine_object_safety_scan": false,
      "torch_version": "2.7.1+cu128",
      "uses_engine_object_safety_scan": true
    },
    {
      "all_actions_blocked_behavior": "execute_least_risk_blocked_action",
      "all_actions_blocked_metric_treatment": "executed_action_reward_and_safety_outcome_recorded_normally",
      "all_blocked_fallback_overrides_exclusion": true,
      "baseline_shared_config": {
        "accident_prob": 0.0,
        "batch_size": 64,
        "collision_penalty": 50.0,
        "deterministic": true,
        "discrete_steering_dim": 3,
        "discrete_throttle_dim": 3,
        "gamma": 0.99,
        "hidden_size": 128,
        "learning_rate": 5e-05,
        "map_blocks": 3,
        "max_episode_steps": 500,
        "out_of_road_penalty": 50.0,
        "progress_every": 25,
        "replay_capacity": 50000,
        "rmst_tau": 500,
        "seed": 31,
        "success_reward": 10.0,
        "target_update_steps": 1000,
        "test_episodes": 300,
        "test_seed": 100000,
        "traffic_density": 0.2,
        "train_episodes": 500
      },
      "baseline_shared_config_sha256": "140b2cdc37a0cb5d8f02656b2bd4b3df5cc9f82da6f2e4f57d1c4dad384cb900",
      "canonical_collision_metrics_include_policy_safety_stop": false,
      "capacity_fallback_all_directional_safety_nonworsening": true,
      "capacity_fallback_any_directional_safety_improves_10_percent": true,
      "capacity_fallback_general_cosine_relaxation": 0.02,
      "capacity_fallback_general_rms_relaxation": 0.1,
      "capacity_fallback_requires_both_relaxed_general_gates": true,
      "capacity_fallback_safety_cosine_rms_gates_remain_strict": true,
      "capacity_fallback_scope": "candidate_hard_limit_permanent_full_or_eviction",
      "completed": true,
      "config_sha256": "c27e7f2ef1cf2e723a40d7f1a1478453889c62d831b433ce980300177b7f28a2",
      "created_at_unix": 1784512324.3434787,
      "critical_config": {
        "accident_prob": 0.0,
        "auto_calibrate_thresholds": true,
        "batch_size": 64,
        "calibration_max_pairs": 20000,
        "calibration_state_count": 3000,
        "candidate_batch_evict_count": 25,
        "candidate_centroid_shift_threshold": 0.01,
        "candidate_distance_threshold": 0.25,
        "candidate_hard_limit": 150,
        "candidate_promotion_visits": 4,
        "candidate_recent_protection_episodes": 3,
        "candidate_safety_distance_threshold": 0.25,
        "candidate_similarity_threshold": 0.9,
        "candidate_stable_updates": 2,
        "capacity_fallback_general_variation": 0.1,
        "capacity_fallback_safety_improvement": 0.1,
        "capacity_review_interval": 25,
        "centroid_shift_threshold": 0.01,
        "centroid_stability_distance_threshold": 0.1,
        "centroid_stable_updates": 3,
        "close_enough_fallback": true,
        "collision_penalty": 50.0,
        "deterministic": true,
        "discrete_steering_dim": 3,
        "discrete_throttle_dim": 3,
        "gamma": 0.99,
        "general_cosine_relaxation": 0.02,
        "general_rms_relaxation": 0.02,
        "hazard_memory_capacity": 125,
        "hazard_memory_fraction": 0.25,
        "hidden_size": 128,
        "hybrid_design_version": "karthikeya27adv8_two_pass_fail_closed_pure_dqn_final20_v3",
        "learning_rate": 5e-05,
        "map_blocks": 3,
        "max_candidate_centroid_updates": 4,
        "max_centroid_updates": 10,
        "max_episode_steps": 500,
        "max_state_candidates": 125,
        "max_state_pools": 500,
        "maximum_pool_capacity": 500,
        "minimum_progress_reward": 0.01,
        "out_of_road_penalty": 50.0,
        "pool_storage_dtype": "float32",
        "pool_training_fraction": 0.8,
        "progress_every": 25,
        "replay_capacity": 50000,
        "rmst_event": "collision",
        "rmst_tau": 500,
        "safe_confirmation_visits": 2,
        "safety_distance_threshold": 0.2,
        "safety_horizon_steps": 5,
        "safety_lane_boundary_cap": 10.0,
        "safety_nearest_object_cap": 100.0,
        "safety_similarity_threshold": 0.9,
        "safety_speed_cap": 200.0,
        "safety_speed_fallback_unit": "mps",
        "seed": 31,
        "state_distance_threshold": 0.2,
        "state_similarity_threshold": 0.9,
        "success_reward": 10.0,
        "target_update_steps": 1000,
        "test_episodes": 300,
        "test_seed": 100000,
        "traffic_density": 0.2,
        "train_episodes": 500,
        "warning_block_threshold": 2
      },
      "critical_config_sha256": "b0f29725efef9644ba365a7ed4db4efeab07c9a8c94264f5f028fa5068065fca",
      "cuda_version": "12.8",
      "detailed_results_sha256": "02ca08e3362d7ffa76e9c39e5b955502d00b23aa81e9aee6f4e63a01026fd449",
      "device": "cuda",
      "environment": "MetaDrive",
      "evicted_candidate_history_capacity": 500,
      "evicted_candidate_history_rows_dropped": 138450,
      "evicted_candidate_history_rows_retained": 500,
      "final_training_policy": "pure_dqn_argmax",
      "final_training_uses_engine_object_safety_scan": false,
      "final_training_uses_pool_lookup": false,
      "final_training_uses_safety_masks": false,
      "first_pass_action_policy": "all_nonblocked_actions_once_then_one_unknown_only_pass",
      "frozen_final_training_uses_blocked_filter": false,
      "hazard_blocked_evidence_inheritance_scope": "mutable_training_only",
      "metadrive_version": "unknown",
      "method": "Karthikeya27adv8",
      "method_label": "Karthikeya27adv8",
      "metrics_sha256": "c9598fda8b52ed77661923f6cdf740e2bcd5e3da6591a123775eae140534736e",
      "missing_safety_behavior": "skip_pool_lookup_and_safe_evidence_use_pure_dqn",
      "missing_safety_values_are_never_imputed_as_safe": true,
      "model_selection": "final_training_episode",
      "model_sha256": "ca9682611453b4d647d265848d84e9bdbdddfa079dd09cd210df01bcc662d0a3",
      "near_promotion_candidates_are_never_evicted": true,
      "normal_general_cosine_relaxation": 0.02,
      "normal_general_relaxation_requires_both_gates": true,
      "normal_general_relaxation_safety_gates_remain_strict": true,
      "normal_general_rms_relaxation": 0.02,
      "observation_source": "flattened_metadrive_observation_for_dqn_plus_engine_safety_features_during_first_pool_training_phase_only",
      "phase_runtime": [
        {
          "average_cpu_time_seconds_per_episode": 31.03505905800598,
          "average_wall_time_seconds_per_episode": 3.10407589869175,
          "episodes": 500,
          "method": "Karthikeya27adv8",
          "method_label": "Karthikeya27adv8",
          "phase": "train",
          "phase_cpu_time_seconds": 15522.415795742001,
          "phase_wall_time_seconds": 1555.0900035860104,
          "summed_episode_cpu_time_seconds": 15517.52952900299,
          "summed_episode_wall_time_seconds": 1552.037949345875
        },
        {
          "average_cpu_time_seconds_per_episode": 0.5494957761499912,
          "average_wall_time_seconds_per_episode": 0.5490137356997002,
          "episodes": 300,
          "method": "Karthikeya27adv8",
          "method_label": "Karthikeya27adv8",
          "phase": "test",
          "phase_cpu_time_seconds": 166.76606387900028,
          "phase_wall_time_seconds": 166.62000071399962,
          "summed_episode_cpu_time_seconds": 164.84873284499736,
          "summed_episode_wall_time_seconds": 164.70412070991006
        }
      ],
      "policy_safety_stop_audit_counts_stop_as_failure": true,
      "policy_safety_stop_metrics_sha256": "4d5bc22c94fa2b231400a9bc8ac6c945bb2003097819b4ca4962c8b9d97fa7e3",
      "post_first_pass_blocked_actions_eligible": false,
      "post_first_pass_selection": "80_percent_eligible_dqn_max_20_percent_unknown_random_with_greedy_fallback_when_no_unknown",
      "python_version": "3.11.15",
      "results_sha256": "6e9e448e47bd7d06bee39ef0359755c58263d7ee3b6e4695260124ef6c68cc8c",
      "runtime_statistics_sha256": "bce36d45b8e553f1762ed11ca7a4c9f3f82d1911f4e11a4b5e212fc7ed588952",
      "safety_memory_sha256": "c8b774e479df2eff46e970221cdeeb993816f49bde93845287832d2f4b177d1d",
      "scheduled_unknown_passes": 1,
      "seed": 31,
      "state_candidate_statistics_sha256": "377e0c874bde30056ff649703617d7a7833cda0ea1c6a94613c9447795e991a5",
      "state_hazard_memory_statistics_sha256": "46d0f2422582a7c84229f37ad6d43e95a562d446f313b0666aa504a797caabbb",
      "state_matching_calibration_sha256": "15858611860b91003287530ae9d11dd9d62dbc2d30dd7e52abc16fdee5d4109e",
      "state_matching_rejection_statistics_sha256": "1c9a02aa120e0d3efed34e1c902af2d6e01be046627ac313843da6c461b4b41e",
      "state_pool_capacity_growth_sha256": "6043096bb6a6d44144a637aff27040f0a7599b0067823748a8a096efe355afd1",
      "state_pool_statistics_sha256": "a01f74871a1bb1b09ba29e66c8cccc38caf9c4cfd2ae728618d834b379395895",
      "state_retired_pool_statistics_sha256": "3d2f67cf3b1cfb821132b863ca06a21631fb34ff0c692167ac8844e513aff79e",
      "test_policy": "final_trained_frozen_dqn_argmax",
      "test_uses_engine_object_safety_scan": false,
      "test_uses_safety_masks": false,
      "torch_version": "2.7.1+cu128",
      "unknown_pass_excludes_blocked_actions": true,
      "unknown_pass_retirement_waits_for_final_safety_horizon": true,
      "uses_engine_object_safety_scan": true
    },
    {
      "all_actions_blocked_behavior": "execute_least_risk_blocked_action",
      "all_actions_blocked_metric_treatment": "executed_action_reward_and_safety_outcome_recorded_normally",
      "all_blocked_fallback_overrides_exclusion": true,
      "baseline_shared_config": {
        "accident_prob": 0.0,
        "batch_size": 64,
        "collision_penalty": 50.0,
        "deterministic": true,
        "discrete_steering_dim": 3,
        "discrete_throttle_dim": 3,
        "gamma": 0.99,
        "hidden_size": 128,
        "learning_rate": 5e-05,
        "map_blocks": 3,
        "max_episode_steps": 500,
        "out_of_road_penalty": 50.0,
        "progress_every": 25,
        "replay_capacity": 50000,
        "rmst_tau": 500,
        "seed": 31,
        "success_reward": 10.0,
        "target_update_steps": 1000,
        "test_episodes": 300,
        "test_seed": 100000,
        "traffic_density": 0.2,
        "train_episodes": 500
      },
      "baseline_shared_config_sha256": "140b2cdc37a0cb5d8f02656b2bd4b3df5cc9f82da6f2e4f57d1c4dad384cb900",
      "canonical_collision_metrics_include_policy_safety_stop": false,
      "capacity_fallback_all_directional_safety_nonworsening": true,
      "capacity_fallback_any_directional_safety_improves_10_percent": true,
      "capacity_fallback_general_cosine_relaxation": 0.02,
      "capacity_fallback_general_rms_relaxation": 0.1,
      "capacity_fallback_requires_both_relaxed_general_gates": true,
      "capacity_fallback_safety_cosine_rms_gates_remain_strict": true,
      "capacity_fallback_scope": "candidate_hard_limit_permanent_full_or_eviction",
      "completed": true,
      "config_sha256": "a78fcb36bbf345c36390a27896a1efd55c0089f5d98c6db229736452a8b373c2",
      "created_at_unix": 1784631180.4295964,
      "critical_config": {
        "accident_prob": 0.0,
        "auto_calibrate_thresholds": true,
        "batch_size": 64,
        "calibration_max_pairs": 20000,
        "calibration_state_count": 3000,
        "candidate_batch_evict_count": 25,
        "candidate_centroid_shift_threshold": 0.01,
        "candidate_distance_threshold": 0.25,
        "candidate_hard_limit": 150,
        "candidate_promotion_visits": 3,
        "candidate_recent_protection_episodes": 3,
        "candidate_safety_distance_threshold": 0.25,
        "candidate_similarity_threshold": 0.9,
        "candidate_stable_updates": 2,
        "capacity_fallback_general_variation": 0.1,
        "capacity_fallback_safety_improvement": 0.1,
        "capacity_review_interval": 25,
        "centroid_shift_threshold": 0.01,
        "centroid_stability_distance_threshold": 0.1,
        "centroid_stable_updates": 3,
        "close_enough_fallback": true,
        "collision_penalty": 50.0,
        "deterministic": true,
        "discrete_steering_dim": 3,
        "discrete_throttle_dim": 3,
        "gamma": 0.99,
        "general_cosine_relaxation": 0.02,
        "general_rms_relaxation": 0.02,
        "hazard_memory_capacity": 125,
        "hazard_memory_fraction": 0.25,
        "hidden_size": 128,
        "hybrid_design_version": "karthikeya27adv20_two_pass_promotion3_retired_dqn_max_unblocked_pure_dqn_final20_v1",
        "learning_rate": 5e-05,
        "map_blocks": 3,
        "max_candidate_centroid_updates": 4,
        "max_centroid_updates": 10,
        "max_episode_steps": 500,
        "max_state_candidates": 125,
        "max_state_pools": 500,
        "maximum_pool_capacity": 500,
        "minimum_progress_reward": 0.01,
        "out_of_road_penalty": 50.0,
        "pool_storage_dtype": "float32",
        "pool_training_fraction": 0.8,
        "progress_every": 25,
        "replay_capacity": 50000,
        "rmst_event": "collision",
        "rmst_tau": 500,
        "safe_confirmation_visits": 2,
        "safety_distance_threshold": 0.2,
        "safety_horizon_steps": 5,
        "safety_lane_boundary_cap": 10.0,
        "safety_nearest_object_cap": 100.0,
        "safety_similarity_threshold": 0.9,
        "safety_speed_cap": 200.0,
        "safety_speed_fallback_unit": "mps",
        "seed": 31,
        "state_distance_threshold": 0.2,
        "state_similarity_threshold": 0.9,
        "success_reward": 10.0,
        "target_update_steps": 1000,
        "test_episodes": 300,
        "test_seed": 100000,
        "traffic_density": 0.2,
        "train_episodes": 500,
        "warning_block_threshold": 2
      },
      "critical_config_sha256": "d32e55a73b0caa8f0a702bad26e95e2654303ef3c796735a0eb08a155aff6531",
      "cuda_version": "12.8",
      "detailed_results_sha256": "0eba96377001a727e6723fa1f507f4588ba81c60d8ebc05a84d0ebb2bb48f298",
      "device": "cuda",
      "environment": "MetaDrive",
      "evicted_candidate_history_capacity": 500,
      "evicted_candidate_history_rows_dropped": 60750,
      "evicted_candidate_history_rows_retained": 500,
      "final_training_policy": "pure_dqn_argmax",
      "final_training_uses_engine_object_safety_scan": false,
      "final_training_uses_pool_lookup": false,
      "final_training_uses_safety_masks": false,
      "first_pass_action_policy": "fresh_dqn_max_from_remaining_nonblocked_actions_until_all_are_tried_once_then_one_unknown_only_pass",
      "frozen_final_training_uses_blocked_filter": false,
      "hazard_blocked_evidence_inheritance_scope": "mutable_training_only",
      "metadrive_version": "unknown",
      "method": "Karthikeya27adv20",
      "method_label": "Karthikeya27adv20",
      "metrics_sha256": "33cfc5b6fb1faa86e23c820afaf8d628dce97f44cd870777572d15fb386761cc",
      "missing_safety_behavior": "skip_pool_lookup_and_safe_evidence_use_pure_dqn",
      "missing_safety_values_are_never_imputed_as_safe": true,
      "model_selection": "final_training_episode",
      "model_sha256": "035d60eeaa9c1cbea8fc89108215f05381fbe8623a16eb267a6e703d62a85b32",
      "near_promotion_candidates_are_never_evicted": true,
      "normal_general_cosine_relaxation": 0.02,
      "normal_general_relaxation_requires_both_gates": true,
      "normal_general_relaxation_safety_gates_remain_strict": true,
      "normal_general_rms_relaxation": 0.02,
      "observation_source": "flattened_metadrive_observation_for_dqn_plus_engine_safety_features_during_first_pool_training_phase_only",
      "phase_runtime": [
        {
          "average_cpu_time_seconds_per_episode": 18.486739148017975,
          "average_wall_time_seconds_per_episode": 2.0902659071459913,
          "episodes": 500,
          "method": "Karthikeya27adv20",
          "method_label": "Karthikeya27adv20",
          "phase": "train",
          "phase_cpu_time_seconds": 9248.414748928,
          "phase_wall_time_seconds": 1048.2476336139998,
          "summed_episode_cpu_time_seconds": 9243.369574008988,
          "summed_episode_wall_time_seconds": 1045.1329535729956
        },
        {
          "average_cpu_time_seconds_per_episode": 1.216178274236548,
          "average_wall_time_seconds_per_episode": 1.215118797346698,
          "episodes": 300,
          "method": "Karthikeya27adv20",
          "method_label": "Karthikeya27adv20",
          "phase": "test",
          "phase_cpu_time_seconds": 366.7574550139998,
          "phase_wall_time_seconds": 366.43805871099994,
          "summed_episode_cpu_time_seconds": 364.8534822709644,
          "summed_episode_wall_time_seconds": 364.5356392040094
        }
      ],
      "policy_safety_stop_audit_counts_stop_as_failure": true,
      "policy_safety_stop_metrics_sha256": "3a51e95448b1b2194be1cbd687f5a4363327ff304dfc830effe0d259561865af",
      "post_first_pass_blocked_actions_eligible": false,
      "post_first_pass_selection": "fresh_dqn_max_across_safe_and_unknown_blocked_excluded",
      "python_version": "3.11.15",
      "results_sha256": "c4bbc8298eab4055d056da68478e227680c8617f58f6c1fe8c07e99b2e5501d6",
      "runtime_statistics_sha256": "bfa81a1f1ee83e67290e9ab32e0b88f01454a9a19774f806441548acac3b300d",
      "safety_memory_sha256": "c3ba9ca084faf6e184db48cf9da1f1473d6208527b8b244a87f47cb55eac482d",
      "scheduled_unknown_passes": 1,
      "seed": 31,
      "state_candidate_statistics_sha256": "80ce30bb7d4a86bb0400b9bb8564864ef42d6b767cb91252078ae79be1933e20",
      "state_hazard_memory_statistics_sha256": "f8b64474cb03ab51e198b4981cd870ab56d307e47a21602295ab3d6b711cd010",
      "state_matching_calibration_sha256": "15858611860b91003287530ae9d11dd9d62dbc2d30dd7e52abc16fdee5d4109e",
      "state_matching_rejection_statistics_sha256": "b97a9ed277a434020862e1e48b4790d1d4329bf6413a8a8e4227c4536c1ae700",
      "state_pool_capacity_growth_sha256": "6043096bb6a6d44144a637aff27040f0a7599b0067823748a8a096efe355afd1",
      "state_pool_statistics_sha256": "735b9fe187983bb9cac85c701391f68ab322b9df095d323bab9a2dae9fbdca0f",
      "state_retired_pool_statistics_sha256": "029767429f5ee13a3af835836ad51846ad5bd77f192809b8a029b23184d924c3",
      "test_policy": "final_trained_frozen_dqn_argmax",
      "test_uses_engine_object_safety_scan": false,
      "test_uses_safety_masks": false,
      "torch_version": "2.7.1+cu128",
      "unknown_pass_excludes_blocked_actions": true,
      "unknown_pass_retirement_waits_for_final_safety_horizon": true,
      "uses_engine_object_safety_scan": true
    },
    {
      "action_mask_bits": 9,
      "action_mask_full_value": 511,
      "all_actions_blocked_behavior": "execute_least_risk_blocked_action",
      "all_actions_blocked_metric_treatment": "executed_action_reward_and_safety_outcome_recorded_normally",
      "all_blocked_fallback_overrides_exclusion": true,
      "baseline_shared_config": {
        "accident_prob": 0.0,
        "batch_size": 64,
        "collision_penalty": 50.0,
        "deterministic": true,
        "discrete_steering_dim": 3,
        "discrete_throttle_dim": 3,
        "gamma": 0.99,
        "hidden_size": 128,
        "learning_rate": 5e-05,
        "map_blocks": 3,
        "max_episode_steps": 500,
        "out_of_road_penalty": 50.0,
        "progress_every": 25,
        "replay_capacity": 50000,
        "rmst_tau": 500,
        "seed": 31,
        "success_reward": 10.0,
        "target_update_steps": 1000,
        "test_episodes": 300,
        "test_seed": 100000,
        "traffic_density": 0.2,
        "train_episodes": 500
      },
      "baseline_shared_config_sha256": "140b2cdc37a0cb5d8f02656b2bd4b3df5cc9f82da6f2e4f57d1c4dad384cb900",
      "canonical_collision_metrics_include_policy_safety_stop": false,
      "capacity_fallback_all_directional_safety_nonworsening": true,
      "capacity_fallback_any_directional_safety_improves_10_percent": true,
      "capacity_fallback_general_cosine_relaxation": 0.02,
      "capacity_fallback_general_rms_relaxation": 0.1,
      "capacity_fallback_requires_both_relaxed_general_gates": true,
      "capacity_fallback_safety_cosine_rms_gates_remain_strict": true,
      "capacity_fallback_scope": "candidate_hard_limit_permanent_full_or_eviction",
      "completed": true,
      "config_sha256": "493270658b52aa2584658055ec79e51dff5cf721a4c6ef87d6d348a06e1bef49",
      "created_at_unix": 1784672598.970112,
      "critical_config": {
        "accident_prob": 0.0,
        "auto_calibrate_thresholds": true,
        "batch_size": 64,
        "calibration_max_pairs": 20000,
        "calibration_state_count": 3000,
        "candidate_batch_evict_count": 25,
        "candidate_centroid_shift_threshold": 0.01,
        "candidate_distance_threshold": 0.25,
        "candidate_hard_limit": 150,
        "candidate_promotion_visits": 3,
        "candidate_recent_protection_episodes": 3,
        "candidate_safety_distance_threshold": 0.25,
        "candidate_similarity_threshold": 0.9,
        "candidate_stable_updates": 2,
        "capacity_fallback_general_variation": 0.1,
        "capacity_fallback_safety_improvement": 0.1,
        "capacity_review_interval": 25,
        "centroid_shift_threshold": 0.01,
        "centroid_stability_distance_threshold": 0.1,
        "centroid_stable_updates": 3,
        "close_enough_fallback": true,
        "collision_penalty": 50.0,
        "deterministic": true,
        "discrete_steering_dim": 3,
        "discrete_throttle_dim": 3,
        "gamma": 0.99,
        "general_cosine_relaxation": 0.02,
        "general_rms_relaxation": 0.02,
        "hazard_memory_capacity": 125,
        "hazard_memory_fraction": 0.25,
        "hidden_size": 128,
        "hybrid_design_version": "karthikeya27adv23_one_pass_promotion3_candidate_nearest_active_hazard_masks_retired_dqn_max_unblocked_candidate_retired_hazard_safe_half_priority_horizon4_pure_dqn_final20_v2",
        "learning_rate": 5e-05,
        "map_blocks": 3,
        "max_candidate_centroid_updates": 4,
        "max_centroid_updates": 10,
        "max_episode_steps": 500,
        "max_state_candidates": 125,
        "max_state_pools": 500,
        "maximum_pool_capacity": 500,
        "minimum_progress_reward": 0.01,
        "out_of_road_penalty": 50.0,
        "pool_storage_dtype": "float32",
        "pool_training_fraction": 0.8,
        "progress_every": 25,
        "replay_capacity": 50000,
        "rmst_event": "collision",
        "rmst_tau": 500,
        "safe_confirmation_visits": 2,
        "safety_distance_threshold": 0.2,
        "safety_horizon_steps": 4,
        "safety_lane_boundary_cap": 10.0,
        "safety_nearest_object_cap": 100.0,
        "safety_similarity_threshold": 0.9,
        "safety_speed_cap": 200.0,
        "safety_speed_fallback_unit": "mps",
        "seed": 31,
        "state_distance_threshold": 0.2,
        "state_similarity_threshold": 0.9,
        "success_reward": 10.0,
        "target_update_steps": 1000,
        "test_episodes": 300,
        "test_seed": 100000,
        "traffic_density": 0.2,
        "train_episodes": 500,
        "warning_block_threshold": 2
      },
      "critical_config_sha256": "3fb5282297f41d400ae6a12383c8a695a97119c977b3268cdab6789000640316",
      "cuda_version": "12.8",
      "detailed_results_sha256": "c32cf3a36d5be4ecd0fc63807520103ceadf15da8ad0d54bb6ff1fab6ce9db8a",
      "device": "cuda",
      "environment": "MetaDrive",
      "environment_action_count": 9,
      "environment_factory": "__main__:make_env",
      "evicted_candidate_history_capacity": 500,
      "evicted_candidate_history_rows_dropped": 72799,
      "evicted_candidate_history_rows_retained": 500,
      "final_training_policy": "pure_dqn_argmax",
      "final_training_uses_engine_object_safety_scan": false,
      "final_training_uses_pool_lookup": false,
      "final_training_uses_safety_masks": false,
      "first_pass_action_policy": "fresh_dqn_max_from_remaining_nonblocked_actions_until_all_are_tried_once_then_retire",
      "frozen_final_training_uses_blocked_filter": false,
      "hazard_blocked_evidence_inheritance_scope": "mutable_training_only",
      "metadrive_version": "unknown",
      "method": "Karthikeya27adv23",
      "method_label": "Karthikeya27adv23",
      "metrics_sha256": "cf367ce5a64c90529dd6cff124c97331fd8bb2438159c6eb6ea4e7b28e63c4ae",
      "missing_safety_behavior": "skip_pool_lookup_and_safe_evidence_use_pure_dqn",
      "missing_safety_values_are_never_imputed_as_safe": true,
      "model_selection": "final_training_episode",
      "model_sha256": "38e87566e110dc87421ba09db3d4338778f0c636e5d4958a974c736fedcb07be",
      "near_promotion_candidates_are_never_evicted": true,
      "normal_general_cosine_relaxation": 0.02,
      "normal_general_relaxation_requires_both_gates": true,
      "normal_general_relaxation_safety_gates_remain_strict": true,
      "normal_general_rms_relaxation": 0.02,
      "observation_source": "flattened_metadrive_observation_for_dqn_plus_engine_safety_features_during_first_pool_training_phase_only",
      "phase_runtime": [
        {
          "average_cpu_time_seconds_per_episode": 18.788396886700006,
          "average_wall_time_seconds_per_episode": 1.7290700755860307,
          "episodes": 500,
          "method": "Karthikeya27adv23",
          "method_label": "Karthikeya27adv23",
          "phase": "train",
          "phase_cpu_time_seconds": 9399.385012543,
          "phase_wall_time_seconds": 867.5513924719999,
          "summed_episode_cpu_time_seconds": 9394.198443350004,
          "summed_episode_wall_time_seconds": 864.5350377930154
        },
        {
          "average_cpu_time_seconds_per_episode": 0.20574101927331867,
          "average_wall_time_seconds_per_episode": 0.20553924639646234,
          "episodes": 300,
          "method": "Karthikeya27adv23",
          "method_label": "Karthikeya27adv23",
          "phase": "test",
          "phase_cpu_time_seconds": 63.586761602999104,
          "phase_wall_time_seconds": 63.52469458599808,
          "summed_episode_cpu_time_seconds": 61.7223057819956,
          "summed_episode_wall_time_seconds": 61.66177391893871
        }
      ],
      "policy_safety_stop_audit_counts_stop_as_failure": true,
      "policy_safety_stop_metrics_sha256": "49eda248ed66701de230b233d14c30086614646a4435d28aeeeb293e7b7dfdb4",
      "post_first_pass_blocked_actions_eligible": false,
      "post_first_pass_selection": "fresh_dqn_max_across_safe_and_unknown_blocked_excluded",
      "python_version": "3.11.15",
      "results_sha256": "94ba521c7e5ab7c0a2196445fe0c47e7781726347f96a9799ade9483b9b8f383",
      "runtime_statistics_sha256": "0d8d075d3012658683aed10b352fb4768e7ee1e81ba18eaf45a27716a3472784",
      "safety_extractor": "__main__:extract_safety_vector",
      "safety_memory_sha256": "62fea3371f88d1d0b16d3612240d6ea24b28ba2003a87cda7899e128fe3711e8",
      "scheduled_unknown_passes": 0,
      "seed": 31,
      "state_candidate_statistics_sha256": "2530d9bf9e4e9979f0848ddb3306b7747a6ab90dbf19390acc4c5d910743e257",
      "state_hazard_memory_statistics_sha256": "0d0fc399ef6f25192d319feeefd56e86720e446463ce5e76b05b7c9b7ba95978",
      "state_matching_calibration_sha256": "15858611860b91003287530ae9d11dd9d62dbc2d30dd7e52abc16fdee5d4109e",
      "state_matching_rejection_statistics_sha256": "10f2481a2f84d97eec977a5706b9a3c7f15cacecb61851d31a38bba8fcad98fc",
      "state_pool_capacity_growth_sha256": "6043096bb6a6d44144a637aff27040f0a7599b0067823748a8a096efe355afd1",
      "state_pool_statistics_sha256": "fb98176e12fb4fd7639735c4ef65218a9b6fcef3d7701e3d92c537385f13f3fb",
      "state_retired_pool_statistics_sha256": "9c570be3122aba222398cba038fa8dc08f21476fdb00625cb9dc41dbfbce41c7",
      "step_info_parser": "__main__:parse_step_info",
      "test_policy": "final_trained_frozen_dqn_argmax",
      "test_uses_engine_object_safety_scan": false,
      "test_uses_safety_masks": false,
      "torch_version": "2.7.1+cu128",
      "unknown_pass_excludes_blocked_actions": false,
      "unknown_pass_retirement_waits_for_final_safety_horizon": false,
      "uses_engine_object_safety_scan": true
    }
  ],
  "observation_source": "method_specific_see_manifests",
  "seed": 31,
  "uses_engine_object_safety_scan": true
}