{
  "critical_config": {
    "accident_prob": 0.0,
    "batch_size": 64,
    "collision_penalty": 50.0,
    "deterministic": true,
    "discrete_steering_dim": 3,
    "discrete_throttle_dim": 3,
    "epsilon": 0.2,
    "gamma": 0.99,
    "hidden_size": 128,
    "learning_rate": 5e-05,
    "map_blocks": 3,
    "max_episode_steps": 500,
    "out_of_road_penalty": 50.0,
    "progress_every": 25,
    "replay_capacity": 50000,
    "rmst_tau": 500,
    "seed": 85,
    "success_reward": 10.0,
    "target_update_steps": 1000,
    "test_episodes": 300,
    "test_seed": 100000,
    "traffic_density": 0.2,
    "train_episodes": 500
  },
  "critical_config_sha256": "8f969743b6c06565eaefb5d93be4a37ef935a0f05ba3e0d8d7628b375e7caf9c",
  "environment": "MetaDrive",
  "method_baseline_shared_config_sha256": {
    "Karthikeya27adv": null,
    "Karthikeya27adv20": "5264304d8050ee0e4d1997f76d2e81a27bc509df456f9804c2cdc8c5d8b2a0bf",
    "Karthikeya27adv23": "5264304d8050ee0e4d1997f76d2e81a27bc509df456f9804c2cdc8c5d8b2a0bf",
    "Karthikeya27adv8": "5264304d8050ee0e4d1997f76d2e81a27bc509df456f9804c2cdc8c5d8b2a0bf",
    "ch6b": null
  },
  "method_critical_config_sha256": {
    "Karthikeya27adv": "9eef386ee3bf51d0f939aa348b53b70a6e93151446086a5c1321e5222d455064",
    "Karthikeya27adv20": "7bb7ae7bafe89c66ef1be43343c8dcebae7c2f4922b11072dafb45a45ec0c842",
    "Karthikeya27adv23": "a38d960f79ed4ca1904bdc8f894688e2ee7963687cf6ee405b8f79c3923d91e6",
    "Karthikeya27adv8": "6dd40abc278712fbed3898a3125fdf074e1628488e5e2d9d85646b4b25562ecf",
    "ch6b": "8f969743b6c06565eaefb5d93be4a37ef935a0f05ba3e0d8d7628b375e7caf9c"
  },
  "method_engine_object_safety_scan": {
    "Karthikeya27adv": true,
    "Karthikeya27adv20": true,
    "Karthikeya27adv23": true,
    "Karthikeya27adv8": true,
    "ch6b": false
  },
  "method_observation_sources": {
    "Karthikeya27adv": "flattened_metadrive_observation_plus_engine_safety_features",
    "Karthikeya27adv20": "flattened_metadrive_observation_for_dqn_plus_engine_safety_features_during_first_pool_training_phase_only",
    "Karthikeya27adv23": "flattened_metadrive_observation_for_dqn_plus_engine_safety_features_during_first_pool_training_phase_only",
    "Karthikeya27adv8": "flattened_metadrive_observation_for_dqn_plus_engine_safety_features_during_first_pool_training_phase_only",
    "ch6b": "flattened_metadrive_observation_only"
  },
  "methods": [
    {
      "completed": true,
      "config_sha256": "df234d740f30569e07f68d7bd0412e47b960ca91cd26eebc8673d8b4a099b8c3",
      "created_at_unix": 1784469035.6186135,
      "critical_config": {
        "accident_prob": 0.0,
        "auto_calibrate_thresholds": true,
        "batch_size": 64,
        "calibration_max_pairs": 20000,
        "calibration_state_count": 3000,
        "candidate_batch_evict_count": 25,
        "candidate_centroid_shift_threshold": 0.01,
        "candidate_distance_threshold": 0.25,
        "candidate_hard_limit": 150,
        "candidate_promotion_visits": 4,
        "candidate_recent_protection_episodes": 3,
        "candidate_safety_distance_threshold": 0.25,
        "candidate_similarity_threshold": 0.9,
        "candidate_stable_updates": 2,
        "capacity_fallback_general_variation": 0.1,
        "capacity_fallback_safety_improvement": 0.1,
        "capacity_review_interval": 25,
        "centroid_shift_threshold": 0.01,
        "centroid_stability_distance_threshold": 0.1,
        "centroid_stable_updates": 3,
        "close_enough_fallback": true,
        "collision_penalty": 50.0,
        "deterministic": true,
        "discrete_steering_dim": 3,
        "discrete_throttle_dim": 3,
        "gamma": 0.99,
        "hazard_memory_capacity": 125,
        "hazard_memory_fraction": 0.25,
        "hidden_size": 128,
        "hybrid_design_version": "karthikeya27adv_directional_safety_fallback_v5",
        "learning_rate": 5e-05,
        "map_blocks": 3,
        "max_candidate_centroid_updates": 4,
        "max_centroid_updates": 10,
        "max_episode_steps": 500,
        "max_state_candidates": 125,
        "max_state_pools": 500,
        "maximum_pool_capacity": 500,
        "minimum_progress_reward": 0.01,
        "out_of_road_penalty": 50.0,
        "pool_storage_dtype": "float32",
        "pool_training_fraction": 0.8,
        "progress_every": 25,
        "replay_capacity": 50000,
        "rmst_event": "collision",
        "rmst_tau": 500,
        "safe_confirmation_visits": 2,
        "safety_distance_threshold": 0.2,
        "safety_horizon_steps": 5,
        "safety_lane_boundary_cap": 10.0,
        "safety_nearest_object_cap": 100.0,
        "safety_similarity_threshold": 0.9,
        "safety_speed_cap": 200.0,
        "safety_speed_fallback_unit": "mps",
        "seed": 85,
        "state_distance_threshold": 0.2,
        "state_similarity_threshold": 0.9,
        "success_reward": 10.0,
        "target_update_steps": 1000,
        "test_episodes": 300,
        "test_seed": 100000,
        "traffic_density": 0.2,
        "train_episodes": 500,
        "warning_block_threshold": 2
      },
      "critical_config_sha256": "9eef386ee3bf51d0f939aa348b53b70a6e93151446086a5c1321e5222d455064",
      "cuda_version": "12.8",
      "detailed_results_sha256": "22dc1511a20e03533cc4eef00af1a5ecfad384a6835c6e420d0f30f60c40c4ea",
      "device": "cuda",
      "environment": "MetaDrive",
      "metadrive_version": "unknown",
      "method": "Karthikeya27adv",
      "method_label": "Karthikeya27adv",
      "metrics_sha256": "0bce38d634d8d2cb5ed20f95e3c4a7ceb7f3d47cb1fd3e1baac359b7f852d92e",
      "model_selection": "final_training_episode",
      "model_sha256": "405b7a959eb11b104f2809a035c0f351c9e44a4b2cd3f6f2053fb1cc7970bc03",
      "observation_source": "flattened_metadrive_observation_plus_engine_safety_features",
      "phase_runtime": [
        {
          "average_cpu_time_seconds_per_episode": 6.580428395058003,
          "average_wall_time_seconds_per_episode": 0.6978636508200725,
          "episodes": 500,
          "method": "Karthikeya27adv",
          "method_label": "Karthikeya27adv",
          "phase": "train",
          "phase_cpu_time_seconds": 3787.400816228,
          "phase_wall_time_seconds": 446.19711639800516,
          "summed_episode_cpu_time_seconds": 3290.2141975290015,
          "summed_episode_wall_time_seconds": 348.93182541003625
        },
        {
          "average_cpu_time_seconds_per_episode": 0.28240445781998763,
          "average_wall_time_seconds_per_episode": 0.28217348953388866,
          "episodes": 300,
          "method": "Karthikeya27adv",
          "method_label": "Karthikeya27adv",
          "phase": "test",
          "phase_cpu_time_seconds": 133.38251617000014,
          "phase_wall_time_seconds": 133.2677719820058,
          "summed_episode_cpu_time_seconds": 84.72133734599629,
          "summed_episode_wall_time_seconds": 84.65204686016659
        }
      ],
      "python_version": "3.11.15",
      "results_sha256": "1e090efb42d38e2184ac679c6ba737b9b1c9bdc3367b232a8a7e224cf7c517fa",
      "runtime_statistics_sha256": "65474f7fae8a3479c90c730a8cc5baa746ee39c73e1cd5e6bb89459cdc76b353",
      "safety_memory_sha256": "45cf5d3feb11a4647c522976ee528fec65f0916ce506aae264b69157076dbe68",
      "seed": 85,
      "state_candidate_statistics_sha256": "3ccf9d4e0085420a00c48e0b750562d344f46140efd304a698187fe8b2e16364",
      "state_hazard_memory_statistics_sha256": "8ed8d9c2b4db4d668fad0104c535ec0bf1d3009c6a25daaca5df16615a766a02",
      "state_matching_calibration_sha256": "d10cf05b05d750b172effeb62a8c0a4ee395681cfe0e54484c7df1b8466ce8f3",
      "state_matching_rejection_statistics_sha256": "b78260c3cd49da536d34d7a1c927eb381b6135283e06dbbd73e2bb08f14e3ed1",
      "state_pool_capacity_growth_sha256": "6043096bb6a6d44144a637aff27040f0a7599b0067823748a8a096efe355afd1",
      "state_pool_statistics_sha256": "a30894a1ebd51a416c6993db1ddfc4aa1299ff7b585b805acd01aa656e7188e5",
      "state_retired_pool_statistics_sha256": "29beb49b7381d65b3fa174b75760c1c411b9cd8dc3df67b6af844d77db75f91e",
      "test_policy": "final_trained_frozen_dqn_argmax",
      "test_uses_engine_object_safety_scan": false,
      "torch_version": "2.7.1+cu128",
      "uses_engine_object_safety_scan": true
    },
    {
      "completed": true,
      "config_sha256": "d65a0c312d80f45042d7354de6ccfedaf87468f2901a7c8831b728c6617aa347",
      "created_at_unix": 1784469559.4618123,
      "critical_config": {
        "accident_prob": 0.0,
        "batch_size": 64,
        "collision_penalty": 50.0,
        "deterministic": true,
        "discrete_steering_dim": 3,
        "discrete_throttle_dim": 3,
        "epsilon": 0.2,
        "gamma": 0.99,
        "hidden_size": 128,
        "learning_rate": 5e-05,
        "map_blocks": 3,
        "max_episode_steps": 500,
        "out_of_road_penalty": 50.0,
        "progress_every": 25,
        "replay_capacity": 50000,
        "rmst_tau": 500,
        "seed": 85,
        "success_reward": 10.0,
        "target_update_steps": 1000,
        "test_episodes": 300,
        "test_seed": 100000,
        "traffic_density": 0.2,
        "train_episodes": 500
      },
      "critical_config_sha256": "8f969743b6c06565eaefb5d93be4a37ef935a0f05ba3e0d8d7628b375e7caf9c",
      "cuda_version": "12.8",
      "device": "cuda",
      "environment": "MetaDrive",
      "metadrive_version": "unknown",
      "method": "ch6b",
      "method_label": "Median 50",
      "metrics_sha256": "e80645c23e9539703c5de7e3d8699c8618a0469eb6194b3e5f9f9e8034ea8583",
      "model_selection": "final_training_episode",
      "model_sha256": "89f3d9786e618ca8174b69c0d6512be0b8c838fded658f0d442d69c2e6332c82",
      "observation_source": "flattened_metadrive_observation_only",
      "phase_runtime": [
        {
          "average_cpu_time_seconds_per_episode": 0.7440307008800009,
          "average_wall_time_seconds_per_episode": 0.7543356452721637,
          "episodes": 500,
          "method": "median_50",
          "method_label": "Median 50",
          "phase": "train",
          "phase_cpu_time_seconds": 374.94881914,
          "phase_wall_time_seconds": 380.09895636899455,
          "summed_episode_cpu_time_seconds": 372.0153504400005,
          "summed_episode_wall_time_seconds": 377.16782263608184
        },
        {
          "average_cpu_time_seconds_per_episode": 0.45986629405666635,
          "average_wall_time_seconds_per_episode": 0.4594597213502857,
          "episodes": 300,
          "method": "median_50",
          "method_label": "Median 50",
          "phase": "test",
          "phase_cpu_time_seconds": 139.88036874000005,
          "phase_wall_time_seconds": 139.7570286419941,
          "summed_episode_cpu_time_seconds": 137.9598882169999,
          "summed_episode_wall_time_seconds": 137.8379164050857
        }
      ],
      "python_version": "3.11.15",
      "results_sha256": "ad566f4b1cda3cc263398467b2185346afac35dd102034ba65a4dfcd9df80100",
      "runtime_statistics_sha256": "e76b031b8c6d9ac11a8e1abdce5158eac5131e7edf5775c02b8c61add0631bc9",
      "seed": 85,
      "test_policy": "final_trained_frozen_dqn_argmax",
      "torch_version": "2.7.1+cu128",
      "uses_engine_object_safety_scan": false
    },
    {
      "all_actions_blocked_behavior": "execute_least_risk_blocked_action",
      "all_actions_blocked_metric_treatment": "executed_action_reward_and_safety_outcome_recorded_normally",
      "all_blocked_fallback_overrides_exclusion": true,
      "baseline_shared_config": {
        "accident_prob": 0.0,
        "batch_size": 64,
        "collision_penalty": 50.0,
        "deterministic": true,
        "discrete_steering_dim": 3,
        "discrete_throttle_dim": 3,
        "gamma": 0.99,
        "hidden_size": 128,
        "learning_rate": 5e-05,
        "map_blocks": 3,
        "max_episode_steps": 500,
        "out_of_road_penalty": 50.0,
        "progress_every": 25,
        "replay_capacity": 50000,
        "rmst_tau": 500,
        "seed": 85,
        "success_reward": 10.0,
        "target_update_steps": 1000,
        "test_episodes": 300,
        "test_seed": 100000,
        "traffic_density": 0.2,
        "train_episodes": 500
      },
      "baseline_shared_config_sha256": "5264304d8050ee0e4d1997f76d2e81a27bc509df456f9804c2cdc8c5d8b2a0bf",
      "canonical_collision_metrics_include_policy_safety_stop": false,
      "capacity_fallback_all_directional_safety_nonworsening": true,
      "capacity_fallback_any_directional_safety_improves_10_percent": true,
      "capacity_fallback_general_cosine_relaxation": 0.02,
      "capacity_fallback_general_rms_relaxation": 0.1,
      "capacity_fallback_requires_both_relaxed_general_gates": true,
      "capacity_fallback_safety_cosine_rms_gates_remain_strict": true,
      "capacity_fallback_scope": "candidate_hard_limit_permanent_full_or_eviction",
      "completed": true,
      "config_sha256": "dce805bc114a2f1d2caf7e05790028da58ce398366e39bc14b23f712b1ae7287",
      "created_at_unix": 1784494554.9469128,
      "critical_config": {
        "accident_prob": 0.0,
        "auto_calibrate_thresholds": true,
        "batch_size": 64,
        "calibration_max_pairs": 20000,
        "calibration_state_count": 3000,
        "candidate_batch_evict_count": 25,
        "candidate_centroid_shift_threshold": 0.01,
        "candidate_distance_threshold": 0.25,
        "candidate_hard_limit": 150,
        "candidate_promotion_visits": 4,
        "candidate_recent_protection_episodes": 3,
        "candidate_safety_distance_threshold": 0.25,
        "candidate_similarity_threshold": 0.9,
        "candidate_stable_updates": 2,
        "capacity_fallback_general_variation": 0.1,
        "capacity_fallback_safety_improvement": 0.1,
        "capacity_review_interval": 25,
        "centroid_shift_threshold": 0.01,
        "centroid_stability_distance_threshold": 0.1,
        "centroid_stable_updates": 3,
        "close_enough_fallback": true,
        "collision_penalty": 50.0,
        "deterministic": true,
        "discrete_steering_dim": 3,
        "discrete_throttle_dim": 3,
        "gamma": 0.99,
        "general_cosine_relaxation": 0.02,
        "general_rms_relaxation": 0.02,
        "hazard_memory_capacity": 125,
        "hazard_memory_fraction": 0.25,
        "hidden_size": 128,
        "hybrid_design_version": "karthikeya27adv8_two_pass_fail_closed_pure_dqn_final20_v3",
        "learning_rate": 5e-05,
        "map_blocks": 3,
        "max_candidate_centroid_updates": 4,
        "max_centroid_updates": 10,
        "max_episode_steps": 500,
        "max_state_candidates": 125,
        "max_state_pools": 500,
        "maximum_pool_capacity": 500,
        "minimum_progress_reward": 0.01,
        "out_of_road_penalty": 50.0,
        "pool_storage_dtype": "float32",
        "pool_training_fraction": 0.8,
        "progress_every": 25,
        "replay_capacity": 50000,
        "rmst_event": "collision",
        "rmst_tau": 500,
        "safe_confirmation_visits": 2,
        "safety_distance_threshold": 0.2,
        "safety_horizon_steps": 5,
        "safety_lane_boundary_cap": 10.0,
        "safety_nearest_object_cap": 100.0,
        "safety_similarity_threshold": 0.9,
        "safety_speed_cap": 200.0,
        "safety_speed_fallback_unit": "mps",
        "seed": 85,
        "state_distance_threshold": 0.2,
        "state_similarity_threshold": 0.9,
        "success_reward": 10.0,
        "target_update_steps": 1000,
        "test_episodes": 300,
        "test_seed": 100000,
        "traffic_density": 0.2,
        "train_episodes": 500,
        "warning_block_threshold": 2
      },
      "critical_config_sha256": "6dd40abc278712fbed3898a3125fdf074e1628488e5e2d9d85646b4b25562ecf",
      "cuda_version": "12.8",
      "detailed_results_sha256": "cd932a8c984b394683f351cb3941657a670e9ef2a4f2f0cb99958237f8219c0f",
      "device": "cuda",
      "environment": "MetaDrive",
      "evicted_candidate_history_capacity": 500,
      "evicted_candidate_history_rows_dropped": 18180,
      "evicted_candidate_history_rows_retained": 500,
      "final_training_policy": "pure_dqn_argmax",
      "final_training_uses_engine_object_safety_scan": false,
      "final_training_uses_pool_lookup": false,
      "final_training_uses_safety_masks": false,
      "first_pass_action_policy": "all_nonblocked_actions_once_then_one_unknown_only_pass",
      "frozen_final_training_uses_blocked_filter": false,
      "hazard_blocked_evidence_inheritance_scope": "mutable_training_only",
      "metadrive_version": "unknown",
      "method": "Karthikeya27adv8",
      "method_label": "Karthikeya27adv8",
      "metrics_sha256": "0103af457a83c89a68ce8d1824f5e9146f592debf3adf609bbc0512e30f6d44b",
      "missing_safety_behavior": "skip_pool_lookup_and_safe_evidence_use_pure_dqn",
      "missing_safety_values_are_never_imputed_as_safe": true,
      "model_selection": "final_training_episode",
      "model_sha256": "39a25d3881e52a308ba6eb10158a664f9971d46e3f500683fe1f6bf6adfdc1b8",
      "near_promotion_candidates_are_never_evicted": true,
      "normal_general_cosine_relaxation": 0.02,
      "normal_general_relaxation_requires_both_gates": true,
      "normal_general_relaxation_safety_gates_remain_strict": true,
      "normal_general_rms_relaxation": 0.02,
      "observation_source": "flattened_metadrive_observation_for_dqn_plus_engine_safety_features_during_first_pool_training_phase_only",
      "phase_runtime": [
        {
          "average_cpu_time_seconds_per_episode": 7.831543631994009,
          "average_wall_time_seconds_per_episode": 0.9105779300902505,
          "episodes": 500,
          "method": "Karthikeya27adv8",
          "method_label": "Karthikeya27adv8",
          "phase": "train",
          "phase_cpu_time_seconds": 3921.78543915,
          "phase_wall_time_seconds": 458.45411090098787,
          "summed_episode_cpu_time_seconds": 3915.7718159970045,
          "summed_episode_wall_time_seconds": 455.2889650451252
        },
        {
          "average_cpu_time_seconds_per_episode": 0.44541360415000025,
          "average_wall_time_seconds_per_episode": 0.4450043765401157,
          "episodes": 300,
          "method": "Karthikeya27adv8",
          "method_label": "Karthikeya27adv8",
          "phase": "test",
          "phase_cpu_time_seconds": 135.5592940790002,
          "phase_wall_time_seconds": 135.43533205900167,
          "summed_episode_cpu_time_seconds": 133.62408124500007,
          "summed_episode_wall_time_seconds": 133.50131296203472
        }
      ],
      "policy_safety_stop_audit_counts_stop_as_failure": true,
      "policy_safety_stop_metrics_sha256": "100dd6774ab242b0bb0f1d51e87cb8a0113f792a66499c40c8e985bc4a38bcfe",
      "post_first_pass_blocked_actions_eligible": false,
      "post_first_pass_selection": "80_percent_eligible_dqn_max_20_percent_unknown_random_with_greedy_fallback_when_no_unknown",
      "python_version": "3.11.15",
      "results_sha256": "13bd2bdbaa0e90fb34b4bc28b926053a4a7cf9010105dcecf0e965ecc742947b",
      "runtime_statistics_sha256": "ea3651445e1f728251222af3fa75ff010eac8a4d54c651ede7649e9425274387",
      "safety_memory_sha256": "d902785af3471c07ee3a0196a564415f4538b04eec7abf4957392a8e2fb8982f",
      "scheduled_unknown_passes": 1,
      "seed": 85,
      "state_candidate_statistics_sha256": "1aaa1db3e02cd9908a9d61887a08e679c347b7a9c066bf0df1d6926c3a7cddd9",
      "state_hazard_memory_statistics_sha256": "d3a846350c890e7f140d79bede03d3efb9ce89b18f802d3d78b978eb807ac3c6",
      "state_matching_calibration_sha256": "da64771876aad4c82834740fccd71d1b2ddf77e8ec0c22a62f3a21bfab87c2f7",
      "state_matching_rejection_statistics_sha256": "f5894ad530937dfab4b55cd8f5a0404397bfc672fd176db50bc5d38ea6ef2d1d",
      "state_pool_capacity_growth_sha256": "6043096bb6a6d44144a637aff27040f0a7599b0067823748a8a096efe355afd1",
      "state_pool_statistics_sha256": "c2128614ad3c4b111144cbad390ddabb891196552330001dcc9c2912784ff778",
      "state_retired_pool_statistics_sha256": "254b5b67258ccd462c73a44fdbe3c4df43b85151bc3a2ec8bbd4c9d6d549fc1e",
      "test_policy": "final_trained_frozen_dqn_argmax",
      "test_uses_engine_object_safety_scan": false,
      "test_uses_safety_masks": false,
      "torch_version": "2.7.1+cu128",
      "unknown_pass_excludes_blocked_actions": true,
      "unknown_pass_retirement_waits_for_final_safety_horizon": true,
      "uses_engine_object_safety_scan": true
    },
    {
      "action_mask_bits": 9,
      "action_mask_full_value": 511,
      "all_actions_blocked_behavior": "execute_least_risk_blocked_action",
      "all_actions_blocked_metric_treatment": "executed_action_reward_and_safety_outcome_recorded_normally",
      "all_blocked_fallback_overrides_exclusion": true,
      "baseline_shared_config": {
        "accident_prob": 0.0,
        "batch_size": 64,
        "collision_penalty": 50.0,
        "deterministic": true,
        "discrete_steering_dim": 3,
        "discrete_throttle_dim": 3,
        "gamma": 0.99,
        "hidden_size": 128,
        "learning_rate": 5e-05,
        "map_blocks": 3,
        "max_episode_steps": 500,
        "out_of_road_penalty": 50.0,
        "progress_every": 25,
        "replay_capacity": 50000,
        "rmst_tau": 500,
        "seed": 85,
        "success_reward": 10.0,
        "target_update_steps": 1000,
        "test_episodes": 300,
        "test_seed": 100000,
        "traffic_density": 0.2,
        "train_episodes": 500
      },
      "baseline_shared_config_sha256": "5264304d8050ee0e4d1997f76d2e81a27bc509df456f9804c2cdc8c5d8b2a0bf",
      "canonical_collision_metrics_include_policy_safety_stop": false,
      "capacity_fallback_all_directional_safety_nonworsening": true,
      "capacity_fallback_any_directional_safety_improves_10_percent": true,
      "capacity_fallback_general_cosine_relaxation": 0.02,
      "capacity_fallback_general_rms_relaxation": 0.1,
      "capacity_fallback_requires_both_relaxed_general_gates": true,
      "capacity_fallback_safety_cosine_rms_gates_remain_strict": true,
      "capacity_fallback_scope": "candidate_hard_limit_permanent_full_or_eviction",
      "completed": true,
      "config_sha256": "c413e9e5483e63ef9f4a75b5151c6a655b719ce52494e3fdfbc67da16bafb0bf",
      "created_at_unix": 1784652333.0798144,
      "critical_config": {
        "accident_prob": 0.0,
        "auto_calibrate_thresholds": true,
        "batch_size": 64,
        "calibration_max_pairs": 20000,
        "calibration_state_count": 3000,
        "candidate_batch_evict_count": 25,
        "candidate_centroid_shift_threshold": 0.01,
        "candidate_distance_threshold": 0.25,
        "candidate_hard_limit": 150,
        "candidate_promotion_visits": 3,
        "candidate_recent_protection_episodes": 3,
        "candidate_safety_distance_threshold": 0.25,
        "candidate_similarity_threshold": 0.9,
        "candidate_stable_updates": 2,
        "capacity_fallback_general_variation": 0.1,
        "capacity_fallback_safety_improvement": 0.1,
        "capacity_review_interval": 25,
        "centroid_shift_threshold": 0.01,
        "centroid_stability_distance_threshold": 0.1,
        "centroid_stable_updates": 3,
        "close_enough_fallback": true,
        "collision_penalty": 50.0,
        "deterministic": true,
        "discrete_steering_dim": 3,
        "discrete_throttle_dim": 3,
        "gamma": 0.99,
        "general_cosine_relaxation": 0.02,
        "general_rms_relaxation": 0.02,
        "hazard_memory_capacity": 125,
        "hazard_memory_fraction": 0.25,
        "hidden_size": 128,
        "hybrid_design_version": "karthikeya27adv23_one_pass_promotion3_candidate_nearest_active_hazard_masks_retired_dqn_max_unblocked_candidate_retired_hazard_safe_half_priority_horizon4_pure_dqn_final20_v2",
        "learning_rate": 5e-05,
        "map_blocks": 3,
        "max_candidate_centroid_updates": 4,
        "max_centroid_updates": 10,
        "max_episode_steps": 500,
        "max_state_candidates": 125,
        "max_state_pools": 500,
        "maximum_pool_capacity": 500,
        "minimum_progress_reward": 0.01,
        "out_of_road_penalty": 50.0,
        "pool_storage_dtype": "float32",
        "pool_training_fraction": 0.8,
        "progress_every": 25,
        "replay_capacity": 50000,
        "rmst_event": "collision",
        "rmst_tau": 500,
        "safe_confirmation_visits": 2,
        "safety_distance_threshold": 0.2,
        "safety_horizon_steps": 4,
        "safety_lane_boundary_cap": 10.0,
        "safety_nearest_object_cap": 100.0,
        "safety_similarity_threshold": 0.9,
        "safety_speed_cap": 200.0,
        "safety_speed_fallback_unit": "mps",
        "seed": 85,
        "state_distance_threshold": 0.2,
        "state_similarity_threshold": 0.9,
        "success_reward": 10.0,
        "target_update_steps": 1000,
        "test_episodes": 300,
        "test_seed": 100000,
        "traffic_density": 0.2,
        "train_episodes": 500,
        "warning_block_threshold": 2
      },
      "critical_config_sha256": "a38d960f79ed4ca1904bdc8f894688e2ee7963687cf6ee405b8f79c3923d91e6",
      "cuda_version": "12.8",
      "detailed_results_sha256": "974c71cdca0aa533c5c79213b8a6b782ff07a384be11fe069bdfbecfb2d2d3af",
      "device": "cuda",
      "environment": "MetaDrive",
      "environment_action_count": 9,
      "environment_factory": "__main__:make_env",
      "evicted_candidate_history_capacity": 500,
      "evicted_candidate_history_rows_dropped": 19811,
      "evicted_candidate_history_rows_retained": 500,
      "final_training_policy": "pure_dqn_argmax",
      "final_training_uses_engine_object_safety_scan": false,
      "final_training_uses_pool_lookup": false,
      "final_training_uses_safety_masks": false,
      "first_pass_action_policy": "fresh_dqn_max_from_remaining_nonblocked_actions_until_all_are_tried_once_then_retire",
      "frozen_final_training_uses_blocked_filter": false,
      "hazard_blocked_evidence_inheritance_scope": "mutable_training_only",
      "metadrive_version": "unknown",
      "method": "Karthikeya27adv23",
      "method_label": "Karthikeya27adv23",
      "metrics_sha256": "b697298ecbd32cb86b1fa47e1a27d481e4cbd69b2358778830bbe79a990407b0",
      "missing_safety_behavior": "skip_pool_lookup_and_safe_evidence_use_pure_dqn",
      "missing_safety_values_are_never_imputed_as_safe": true,
      "model_selection": "final_training_episode",
      "model_sha256": "39dbd0a58af392211593bf4679a3baf5bab9eb69381d23b7b93d6bdfcbf50590",
      "near_promotion_candidates_are_never_evicted": true,
      "normal_general_cosine_relaxation": 0.02,
      "normal_general_relaxation_requires_both_gates": true,
      "normal_general_relaxation_safety_gates_remain_strict": true,
      "normal_general_rms_relaxation": 0.02,
      "observation_source": "flattened_metadrive_observation_for_dqn_plus_engine_safety_features_during_first_pool_training_phase_only",
      "phase_runtime": [
        {
          "average_cpu_time_seconds_per_episode": 7.829667377784007,
          "average_wall_time_seconds_per_episode": 0.9104066694260473,
          "episodes": 500,
          "method": "Karthikeya27adv23",
          "method_label": "Karthikeya27adv23",
          "phase": "train",
          "phase_cpu_time_seconds": 3920.7595022809996,
          "phase_wall_time_seconds": 458.3348011579983,
          "summed_episode_cpu_time_seconds": 3914.8336888920035,
          "summed_episode_wall_time_seconds": 455.20333471302365
        },
        {
          "average_cpu_time_seconds_per_episode": 0.5075721899833191,
          "average_wall_time_seconds_per_episode": 0.5071389012633638,
          "episodes": 300,
          "method": "Karthikeya27adv23",
          "method_label": "Karthikeya27adv23",
          "phase": "test",
          "phase_cpu_time_seconds": 154.17268301400009,
          "phase_wall_time_seconds": 154.04153950699765,
          "summed_episode_cpu_time_seconds": 152.27165699499574,
          "summed_episode_wall_time_seconds": 152.14167037900916
        }
      ],
      "policy_safety_stop_audit_counts_stop_as_failure": true,
      "policy_safety_stop_metrics_sha256": "acfcbd0269d0365082db3378ae78a566ef08245bf0cfbdcfcf6bff1708004a70",
      "post_first_pass_blocked_actions_eligible": false,
      "post_first_pass_selection": "fresh_dqn_max_across_safe_and_unknown_blocked_excluded",
      "python_version": "3.11.15",
      "results_sha256": "cab7d12bf932b4ede2e636ddb421804ef0bb47383f7fcc886175175bfe86cf1f",
      "runtime_statistics_sha256": "579d277c2d9d8d35562c17a4a0db02fc4bf1709258a09a7b9e69ae8b973c162a",
      "safety_extractor": "__main__:extract_safety_vector",
      "safety_memory_sha256": "20baecdd872d9cb4db26982a3c1ba7c4b7674e6050528f945afd07e2b7512dfc",
      "scheduled_unknown_passes": 0,
      "seed": 85,
      "state_candidate_statistics_sha256": "e2c1740fe026bfba7165381ab21c771932cc900384bf07eb37f675c8e02f5b50",
      "state_hazard_memory_statistics_sha256": "4f72a4b74f9d1be51fab81acc6714e7fc180147738a0cf7eaf34518a03dff48a",
      "state_matching_calibration_sha256": "da64771876aad4c82834740fccd71d1b2ddf77e8ec0c22a62f3a21bfab87c2f7",
      "state_matching_rejection_statistics_sha256": "86a78fe94c01795dde5cac31f10a5028b93b028d2c483f7e26d0ffe14f2773b6",
      "state_pool_capacity_growth_sha256": "6043096bb6a6d44144a637aff27040f0a7599b0067823748a8a096efe355afd1",
      "state_pool_statistics_sha256": "fbdc364c5756b9f8ec84b0730263a1e06c694b17f5e123ed5c5ce44afb4a1c7d",
      "state_retired_pool_statistics_sha256": "5bc4a6dbd34706f2c8bd715bec2116f4a8614efa255311acb1ad857d03f8e4fc",
      "step_info_parser": "__main__:parse_step_info",
      "test_policy": "final_trained_frozen_dqn_argmax",
      "test_uses_engine_object_safety_scan": false,
      "test_uses_safety_masks": false,
      "torch_version": "2.7.1+cu128",
      "unknown_pass_excludes_blocked_actions": false,
      "unknown_pass_retirement_waits_for_final_safety_horizon": false,
      "uses_engine_object_safety_scan": true
    },
    {
      "all_actions_blocked_behavior": "execute_least_risk_blocked_action",
      "all_actions_blocked_metric_treatment": "executed_action_reward_and_safety_outcome_recorded_normally",
      "all_blocked_fallback_overrides_exclusion": true,
      "baseline_shared_config": {
        "accident_prob": 0.0,
        "batch_size": 64,
        "collision_penalty": 50.0,
        "deterministic": true,
        "discrete_steering_dim": 3,
        "discrete_throttle_dim": 3,
        "gamma": 0.99,
        "hidden_size": 128,
        "learning_rate": 5e-05,
        "map_blocks": 3,
        "max_episode_steps": 500,
        "out_of_road_penalty": 50.0,
        "progress_every": 25,
        "replay_capacity": 50000,
        "rmst_tau": 500,
        "seed": 85,
        "success_reward": 10.0,
        "target_update_steps": 1000,
        "test_episodes": 300,
        "test_seed": 100000,
        "traffic_density": 0.2,
        "train_episodes": 500
      },
      "baseline_shared_config_sha256": "5264304d8050ee0e4d1997f76d2e81a27bc509df456f9804c2cdc8c5d8b2a0bf",
      "canonical_collision_metrics_include_policy_safety_stop": false,
      "capacity_fallback_all_directional_safety_nonworsening": true,
      "capacity_fallback_any_directional_safety_improves_10_percent": true,
      "capacity_fallback_general_cosine_relaxation": 0.02,
      "capacity_fallback_general_rms_relaxation": 0.1,
      "capacity_fallback_requires_both_relaxed_general_gates": true,
      "capacity_fallback_safety_cosine_rms_gates_remain_strict": true,
      "capacity_fallback_scope": "candidate_hard_limit_permanent_full_or_eviction",
      "completed": true,
      "config_sha256": "d5e1aad8c6d1867395695faea83b896f5d9f62af34ac50155df9cae9607ee514",
      "created_at_unix": 1784665126.5515387,
      "critical_config": {
        "accident_prob": 0.0,
        "auto_calibrate_thresholds": true,
        "batch_size": 64,
        "calibration_max_pairs": 20000,
        "calibration_state_count": 3000,
        "candidate_batch_evict_count": 25,
        "candidate_centroid_shift_threshold": 0.01,
        "candidate_distance_threshold": 0.25,
        "candidate_hard_limit": 150,
        "candidate_promotion_visits": 3,
        "candidate_recent_protection_episodes": 3,
        "candidate_safety_distance_threshold": 0.25,
        "candidate_similarity_threshold": 0.9,
        "candidate_stable_updates": 2,
        "capacity_fallback_general_variation": 0.1,
        "capacity_fallback_safety_improvement": 0.1,
        "capacity_review_interval": 25,
        "centroid_shift_threshold": 0.01,
        "centroid_stability_distance_threshold": 0.1,
        "centroid_stable_updates": 3,
        "close_enough_fallback": true,
        "collision_penalty": 50.0,
        "deterministic": true,
        "discrete_steering_dim": 3,
        "discrete_throttle_dim": 3,
        "gamma": 0.99,
        "general_cosine_relaxation": 0.02,
        "general_rms_relaxation": 0.02,
        "hazard_memory_capacity": 125,
        "hazard_memory_fraction": 0.25,
        "hidden_size": 128,
        "hybrid_design_version": "karthikeya27adv20_single_pass_promotion3_retired_dqn_max_unblocked_horizon4_pure_dqn_final20_v2",
        "learning_rate": 5e-05,
        "map_blocks": 3,
        "max_candidate_centroid_updates": 4,
        "max_centroid_updates": 10,
        "max_episode_steps": 500,
        "max_state_candidates": 125,
        "max_state_pools": 500,
        "maximum_pool_capacity": 500,
        "minimum_progress_reward": 0.01,
        "out_of_road_penalty": 50.0,
        "pool_storage_dtype": "float32",
        "pool_training_fraction": 0.8,
        "progress_every": 25,
        "replay_capacity": 50000,
        "rmst_event": "collision",
        "rmst_tau": 500,
        "safe_confirmation_visits": 2,
        "safety_distance_threshold": 0.2,
        "safety_horizon_steps": 4,
        "safety_lane_boundary_cap": 10.0,
        "safety_nearest_object_cap": 100.0,
        "safety_similarity_threshold": 0.9,
        "safety_speed_cap": 200.0,
        "safety_speed_fallback_unit": "mps",
        "seed": 85,
        "state_distance_threshold": 0.2,
        "state_similarity_threshold": 0.9,
        "success_reward": 10.0,
        "target_update_steps": 1000,
        "test_episodes": 300,
        "test_seed": 100000,
        "traffic_density": 0.2,
        "train_episodes": 500,
        "warning_block_threshold": 2
      },
      "critical_config_sha256": "7bb7ae7bafe89c66ef1be43343c8dcebae7c2f4922b11072dafb45a45ec0c842",
      "cuda_version": "12.8",
      "detailed_results_sha256": "4806b8658ee189c880c5148e9ff435ee0e1a0360e78847a6935c4ce6664e2128",
      "device": "cuda",
      "environment": "MetaDrive",
      "evicted_candidate_history_capacity": 500,
      "evicted_candidate_history_rows_dropped": 22001,
      "evicted_candidate_history_rows_retained": 500,
      "final_training_policy": "pure_dqn_argmax",
      "final_training_uses_engine_object_safety_scan": false,
      "final_training_uses_pool_lookup": false,
      "final_training_uses_safety_masks": false,
      "first_pass_action_policy": "fresh_dqn_max_from_remaining_nonblocked_actions_until_all_are_tried_once_then_retire",
      "frozen_final_training_uses_blocked_filter": false,
      "hazard_blocked_evidence_inheritance_scope": "mutable_training_only",
      "metadrive_version": "unknown",
      "method": "Karthikeya27adv20",
      "method_label": "Karthikeya27adv20",
      "metrics_sha256": "800dbba7973507c6935b2b97269a0d1e017f3d265ce0d5b6da5fe538026d1e6e",
      "missing_safety_behavior": "skip_pool_lookup_and_safe_evidence_use_pure_dqn",
      "missing_safety_values_are_never_imputed_as_safe": true,
      "model_selection": "final_training_episode",
      "model_sha256": "88c70cb16aaf06e33c3d406da0f87a902a3c1fb940d529c42e9fa30dc580d472",
      "near_promotion_candidates_are_never_evicted": true,
      "normal_general_cosine_relaxation": 0.02,
      "normal_general_relaxation_requires_both_gates": true,
      "normal_general_relaxation_safety_gates_remain_strict": true,
      "normal_general_rms_relaxation": 0.02,
      "observation_source": "flattened_metadrive_observation_for_dqn_plus_engine_safety_features_during_first_pool_training_phase_only",
      "phase_runtime": [
        {
          "average_cpu_time_seconds_per_episode": 8.880388976691993,
          "average_wall_time_seconds_per_episode": 1.000241184465849,
          "episodes": 500,
          "method": "Karthikeya27adv20",
          "method_label": "Karthikeya27adv20",
          "phase": "train",
          "phase_cpu_time_seconds": 4446.364387796,
          "phase_wall_time_seconds": 503.2281140240011,
          "summed_episode_cpu_time_seconds": 4440.194488345996,
          "summed_episode_wall_time_seconds": 500.12059223292454
        },
        {
          "average_cpu_time_seconds_per_episode": 0.4873000373166815,
          "average_wall_time_seconds_per_episode": 0.48690126358662383,
          "episodes": 300,
          "method": "Karthikeya27adv20",
          "method_label": "Karthikeya27adv20",
          "phase": "test",
          "phase_cpu_time_seconds": 148.06193886500023,
          "phase_wall_time_seconds": 147.9409827989948,
          "summed_episode_cpu_time_seconds": 146.19001119500444,
          "summed_episode_wall_time_seconds": 146.07037907598715
        }
      ],
      "policy_safety_stop_audit_counts_stop_as_failure": true,
      "policy_safety_stop_metrics_sha256": "54001a47aab655d9554e5e4a308b3d04087f6e6400f235aba8edbc1c1ce5213d",
      "post_first_pass_blocked_actions_eligible": false,
      "post_first_pass_selection": "fresh_dqn_max_across_safe_and_unknown_blocked_excluded",
      "python_version": "3.11.15",
      "results_sha256": "176546707b94104c1119636055e67b33fcf052b31384c0918af11cba90343c06",
      "runtime_statistics_sha256": "c0bf03d92226cfe479030d00741d41e8bebf1408de83bc30cbeb69cbbbbd2265",
      "safety_memory_sha256": "75c1336dc1ff80a3acf66180127037ec60305c8fdbaaa6dfc101aa8dd7619e91",
      "scheduled_unknown_passes": 0,
      "seed": 85,
      "state_candidate_statistics_sha256": "c944a10ac750793b6a754bb02dc27cd3aa052391b42acc4c9128912df2cec324",
      "state_hazard_memory_statistics_sha256": "f6995b5e624cb3efc9bd3fb0a711ac28eba6e29b6a9bdd638b435b17e568d5a1",
      "state_matching_calibration_sha256": "da64771876aad4c82834740fccd71d1b2ddf77e8ec0c22a62f3a21bfab87c2f7",
      "state_matching_rejection_statistics_sha256": "5751efe087a202a644ff5ba237d0a0fefe22104ef44e045c9038c38772479247",
      "state_pool_capacity_growth_sha256": "6043096bb6a6d44144a637aff27040f0a7599b0067823748a8a096efe355afd1",
      "state_pool_statistics_sha256": "0956f15e1dfc16cd18cfbd173b4d463a0d18c9cfba5266f86889249483ca7348",
      "state_retired_pool_statistics_sha256": "10c8df5dfdc92f71118b2698811eb9831d8b0fd133f152f1264546035364e71f",
      "test_policy": "final_trained_frozen_dqn_argmax",
      "test_uses_engine_object_safety_scan": false,
      "test_uses_safety_masks": false,
      "torch_version": "2.7.1+cu128",
      "unknown_pass_excludes_blocked_actions": false,
      "unknown_pass_retirement_waits_for_final_safety_horizon": false,
      "uses_engine_object_safety_scan": true
    }
  ],
  "observation_source": "method_specific_see_manifests",
  "seed": 85,
  "uses_engine_object_safety_scan": true
}